pygibbs/__init__.py
pygibbs/dms.cpython-37m-darwin.so
pygibbs/solvers.cpython-37m-darwin.so
pygibbs/utils.cpython-37m-darwin.so
pygibbs-0.0.2.dist-info/LICENSE
pygibbs-0.0.2.dist-info/METADATA
pygibbs-0.0.2.dist-info/WHEEL
pygibbs-0.0.2.dist-info/top_level.txt
pygibbs-0.0.2.dist-info/RECORD
